saa-0.0.9.dist-info/METADATA
saa-0.0.9.dist-info/WHEEL
saa-0.0.9.dist-info/entry_points.txt
saa-0.0.9.dist-info/licenses/LICENSE
saa/__init__.py
saa/clock.py
saa/core/__init__.py
saa/core/language.py
saa/core/numbers.py
saa/core/plugins.py
saa/core/template.py
saa/core/watch.py
saa/luga/da/__init__.py
saa/luga/de/__init__.py
saa/luga/en/__init__.py
saa/luga/ru/__init__.py
saa/luga/sw/__init__.py
saa/luga/zh/__init__.py
saa-0.0.9.dist-info/RECORD
