Metadata-Version: 2.1
Name: saa
Version: 0.0.9
Summary: Converting time into natural language phrases
Author-Email: "Prayson W. Daniel" <praysonpi@gmail.com>
Requires-Python: >=3.8
